{
  "code": 200,
  "msg": "success",
  "newslist": [
    {
      "content": "爷爷让奶奶一同来下棋，奶奶让爷爷—同去看戏。爷爷奶奶争来争去，小喜和小齐出个好主意。小喜和爷爷下棋，小齐和奶奶看戏，爷爷、奶奶、小喜、小齐笑嘻嘻。"
    },
    {
      "content": "大柴和小柴，帮助爷爷晒白菜，大柴晒的是大白菜，小柴晒的是小白菜。大柴晒了四十四斤四两大白菜，小柴晒了三十三斤三两小白菜，一共晒了七十七斤七两的白菜。"
    },
    {
      "content": "马后面有群鸭，鸭后面打群马，小华忙数马和鸭，小花忙数鸭和马。小华数完说腿的只数共一百二十八，小花数完说头的只数总共五十八。请你动脑算一环，多少马来多少鸭?"
    },
    {
      "content": "火炉膛里有木柴，火炉台上有十三根火柴。小花划火柴点木柴，划不着火柴没点燃木柴。小花再划火柴点木柴，又没划着火柴点燃木柴。火炉台上只剩下七根火柴，小花划火柴浪费了多少火柴？"
    },
    {
      "content": "奶奶家后头一棵稻，一只母鸡咯咯叫，伸长脖子去叼稻，<br/>奶奶奶奶你来看，<br/>是稻吊鸡还是鸡叼稻？"
    },
    {
      "content": "放牛孩子叫阿牛，阿牛放的是老牛。老牛哞哞叫阿牛，阿牛轻轻拉老牛。老牛下河水中游，阿牛过河骑老牛。老牛游水驮阿牛，阿牛放牛骑老牛。"
    },
    {
      "content": "老鸡带小鸡，走东又走西，老鸡唱歌咯咯咯，小鸡叫着叽叽叽。老鸡骂小鸡，你这笨东西，我教你唱咯咯咯，你偏叫着叽叽叽。"
    },
    {
      "content": "红花儿，花儿红。黄花儿，花儿黄。红花儿黄花儿黄又红，黄花儿红花儿红又黄。"
    },
    {
      "content": "精致不是经济，组织不是狙击；把不直念成不急，秩序就会变成继续，也会变成持续，大使变成大喜。"
    },
    {
      "content": "小花小筐手里拿，种了葵花收葵花。小华小篮身上挎，种了蓖麻收蓖麻。小花的葵花花盘大，摘葵花小华帮小花；小华的蓖麻密麻麻，收蓖麻小花帮小华。"
    }
  ]
}